cypher_cell-0.1.6.dist-info/METADATA
cypher_cell-0.1.6.dist-info/WHEEL
cypher_cell-0.1.6.dist-info/licenses/LICENSE
cypher_cell.pyi
cypher_cell/__init__.py
cypher_cell/__init__.pyi
cypher_cell/cypher_cell.pyd
cypher_cell/py.typed
py.typed
cypher_cell-0.1.6.dist-info/RECORD
