Metadata-Version: 2.4
Name: cypher_cell
Version: 0.1.6
Classifier: Development Status :: 5 - Production/Stable
Classifier: Intended Audience :: Developers
Classifier: License :: OSI Approved :: MIT License
Classifier: Operating System :: OS Independent
Classifier: Operating System :: Microsoft :: Windows
Classifier: Operating System :: POSIX :: Linux
Classifier: Operating System :: MacOS
Classifier: Programming Language :: Python :: 3
Classifier: Programming Language :: Python :: 3.10
Classifier: Programming Language :: Python :: 3.11
Classifier: Programming Language :: Python :: 3.12
Classifier: Programming Language :: Python :: 3.13
Classifier: Programming Language :: Python :: 3.14
Classifier: Programming Language :: Rust
Classifier: Topic :: Security
Classifier: Topic :: Software Development :: Libraries :: Python Modules
License-File: LICENSE
Summary: Hardened, self-destructing memory cells for Python secrets, powered by Rust.
Keywords: security,memory,zeroize,mlock,python,rust,ffi,secrets
Author-email: Rivendael <riverb514@gmail.com>
Requires-Python: >=3.10
Project-URL: Homepage, https://github.com/Rivendael/cypher_cell
Project-URL: Repository, https://github.com/Rivendael/cypher_cell
Project-URL: Documentation, https://github.com/Rivendael/cypher_cell#readme
Project-URL: Issues, https://github.com/Rivendael/cypher_cell/issues
